Kobalt/__init__.py
kobalt-0.1.3.dist-info/licenses/LICENSE
kobalt-0.1.3.dist-info/METADATA
kobalt-0.1.3.dist-info/WHEEL
kobalt-0.1.3.dist-info/top_level.txt
kobalt-0.1.3.dist-info/RECORD
