Metadata-Version: 2.4
Name: kobalt
Version: 0.1.3
Summary: Library for download Cobalt Api
Author-email: devKovalsky <xxboxf@gmail.com>
License-Expression: MIT
Project-URL: Homepage, https://github.com/Kovalssky/Kobalt/
Project-URL: Documentation, https://github.com/Kovalssky/Kobalt/README.md
Keywords: Downloader,Cobalt
Requires-Python: >=3.10
License-File: LICENSE
Requires-Dist: requests>=2.25
Dynamic: license-file
